mitmproxy_linux-0.12.5.data/scripts/mitmproxy-linux-redirector
mitmproxy_linux-0.12.5.dist-info/METADATA
mitmproxy_linux-0.12.5.dist-info/WHEEL
mitmproxy_linux/__init__.py
mitmproxy_linux-0.12.5.dist-info/RECORD
