Metadata-Version: 2.4
Name: mitmproxy_linux
Version: 0.12.5
Classifier: Programming Language :: Rust
Classifier: Programming Language :: Python :: Implementation :: CPython
Classifier: Programming Language :: Python :: Implementation :: PyPy
Author: Fabio Valentini <decathorpe@gmail.com>, Maximilian Hils <cargo@maximilianhils.com>
Author-email: Fabio Valentini <decathorpe@gmail.com>, Maximilian Hils <cargo@maximilianhils.com>
License: MIT
Requires-Python: >=3.12
Project-URL: Source Code, https://github.com/mitmproxy/mitmproxy-rs
